micro_restplus_ext/__init__.py
micro_restplus_ext/api.py
micro_restplus_ext/model.py
micro_restplus_ext/namespace.py
micro_restplus_ext/parameters.py
micro_restplus_ext/resource.py
micro_restplus_ext/utils.py
micro_restplus_ext-1.0.0.dist-info/METADATA
micro_restplus_ext-1.0.0.dist-info/WHEEL
micro_restplus_ext-1.0.0.dist-info/top_level.txt
micro_restplus_ext-1.0.0.dist-info/RECORD
