Metadata-Version: 2.1
Name: micro-restplus-ext
Version: 1.0.0
Summary: micro_restplus_ext
Home-page: https://github.com/alhazmy13/restplus_ext
Author: Alhazmy13
Author-email: me@alhazmy13.net
License: MIT
Platform: UNKNOWN
Requires-Dist: micro-api-ext
